lab08 final/lab08/project_1/project_1/project_1.srcs/sources_1/new/LEDModule.v
`timescale 1ns / 1ps

module LEDModule (
    input         clk,
    input         rst,
    input         LEDWrite,
    input  [15:0] writeData,
    output [15:0] leds
);
    reg [15:0] led_reg;

    always @(posedge clk or posedge rst) begin
        if (rst)
            led_reg <= 16'b0;
        else if (LEDWrite)
            led_reg <= writeData;
    end

    assign leds = led_reg;

endmodule

lab08 final/lab08/project_1/project_1/project_1.srcs/sources_1/new/DataMemory.v
module DataMemory (
    input         clk,
    input         MemWrite,
    input         MemRead,
    input  [7:0]  address,      // only lower 8 bits needed (512 locations)
    input  [31:0] write_data,
    output [31:0] read_data
);
    reg [31:0] mem [0:511];
    integer i;
    

    always @(posedge clk)
        if (MemWrite)
            for(i=0;i<4;i=i+1) begin
                mem[address+i] <= write_data[i*8 +:8];
        end
    
    assign read_data = MemRead ? {mem[address+3], mem[address+2],  mem[address+1], mem[address+0]} : 32'b0;
endmodule

lab08 final/lab08/project_1/project_1/project_1.srcs/sources_1/new/AddressDecoder.v
module AddressDecoder (
    input  [9:0] address,
    input        readEnable,
    input        writeEnable,
    output       DataMemWrite,
    output       DataMemRead,
    output       LEDWrite,
    output       SwitchRead
);
    wire isDataMem=(address[9:8]==2'b00);
    wire isLED=(address[9:8]==2'b10);
    wire isSwitch= (address[9:8]==2'b11);

    assign DataMemWrite = isDataMem && writeEnable;
    assign DataMemRead  = isDataMem && readEnable;
    assign LEDWrite     = isLED && writeEnable;
    assign SwitchRead   = isSwitch && readEnable;
endmodule

lab08 final/lab08/project_1/project_1/project_1.srcs/sources_1/new/AddressDecoderTop.v
module addressDecoderTop(
    input         clk, rst,
    input  [31:0] address,
    input         readEnable, writeEnable,
    input  [31:0] writeData,
    input  [15:0] switches,
    output [31:0] readData,
    output [15:0] leds
);
    wire DataMemWrite, DataMemRead, LEDWrite, SwitchRead;
    wire [31:0] memReadData;

    // Address Decoder
    AddressDecoder decoder (
        .address     (address[9:0]),
        .readEnable  (readEnable),
        .writeEnable (writeEnable),
        .DataMemWrite(DataMemWrite),
        .DataMemRead (DataMemRead),
        .LEDWrite    (LEDWrite),
        .SwitchRead  (SwitchRead)
    );

    // Data Memory
    DataMemory dmem (
        .clk        (clk),
        .MemWrite   (DataMemWrite),
        .MemRead    (DataMemRead),
        .address    (address[7:0]),  
        .write_data (writeData),
        .read_data  (memReadData)
    );

    // LED register (from Lab 5)
    LEDModule leds_inst (
        .clk      (clk),
        .rst      (rst),
        .LEDWrite (LEDWrite),
        .writeData(writeData[15:0]),
        .leds     (leds)
    );

    // Read data mux - pick which device's output goes back to CPU
    assign readData = DataMemRead ? memReadData       :
                      SwitchRead  ? {16'b0, switches} :
                                    32'b0;
endmodule

lab08 final/lab08/project_1/project_1/project_1.srcs/sim_1/new/Memorysystemtb.v
`timescale 1ns / 1ps
//////////////////////////////////////////////////////////////////////////////////
// Module Name: MemorySystem_tb
// Description: Testbench for addressDecoderTop
//              Tests:
//              1. Write to Data Memory and read back
//              2. Write to LEDs and verify output
//              3. Read from Switches
//              4. Verify only one enable fires at a time
//////////////////////////////////////////////////////////////////////////////////
module Memorysystemtb;

   
    reg         clk;
    reg         rst;
    reg  [31:0] address;
    reg         readEnable;
    reg         writeEnable;
    reg  [31:0] writeData;
    reg  [15:0] switches;

    // ================================================================
    //  DUT Outputs (observed by testbench)
    // ================================================================
    wire [31:0] readData;
    wire [15:0] leds;

    // ================================================================
    //  Instantiate DUT
    // ================================================================
    addressDecoderTop dut (
        .clk        (clk),
        .rst        (rst),
        .address    (address),
        .readEnable (readEnable),
        .writeEnable(writeEnable),
        .writeData  (writeData),
        .switches   (switches),
        .readData   (readData),
        .leds       (leds)
    );

    // ================================================================
    //  Clock Generation: 100 MHz (10 ns period)
    // ================================================================
    initial clk = 0;
    always #5 clk = ~clk;

    // ================================================================
    //  Task: Write to an address
    // ================================================================
    task do_write;
        input [31:0] addr;
        input [31:0] data;
        begin
            @(negedge clk);         // apply before rising edge
            address     = addr;
            writeData   = data;
            writeEnable = 1;
            readEnable  = 0;
            @(posedge clk);         // write commits here
            #1;                     // small settle time
            writeEnable = 0;
        end
    endtask

    // ================================================================
    //  Task: Read from an address
    // ================================================================
    task do_read;
        input [31:0] addr;
        begin
            @(negedge clk);
            address     = addr;
            writeEnable = 0;
            readEnable  = 1;
            @(posedge clk);
            #1;
            readEnable  = 0;
        end
    endtask

    // ================================================================
    //  Test Results Counter
    // ================================================================
    integer pass_count;
    integer fail_count;

    // ================================================================
    //  Main Test Sequence
    // ================================================================
    initial begin
        // ---- Initialise ----
        pass_count  = 0;
        fail_count  = 0;
        rst         = 1;
        address     = 32'b0;
        readEnable  = 0;
        writeEnable = 0;
        writeData   = 32'b0;
        switches    = 16'b0;

        // Hold reset for 3 cycles
        repeat(3) @(posedge clk);
        #1;
        rst = 0;
        @(posedge clk);

        $display("============================================");
        $display("       MEMORY SYSTEM TESTBENCH START       ");
        $display("============================================");

        // ============================================================
        //  TEST GROUP 1: Data Memory (address[9:8] = 00)
        //  Address range 0 - 511
        // ============================================================
        $display("\n--- TEST GROUP 1: Data Memory Writes & Reads ---");

        // Test 1a: Write 0xDEADBEEF to address 0x00A (location 10)
        do_write(32'h00A, 32'hDEADBEEF);
        $display("T1a: Wrote 0xDEADBEEF to addr 0x00A");

        // Test 1b: Read back from address 0x00A
        do_read(32'h00A);
        if (readData === 32'hDEADBEEF) begin
            $display("T1b: PASS - readData = 0x%08X (expected 0xDEADBEEF)", readData);
            pass_count = pass_count + 1;
        end else begin
            $display("T1b: FAIL - readData = 0x%08X (expected 0xDEADBEEF)", readData);
            fail_count = fail_count + 1;
        end

        // Test 1c: Write 0x12345678 to address 0x001 (location 1)
        do_write(32'h001, 32'h12345678);
        $display("T1c: Wrote 0x12345678 to addr 0x001");

        // Test 1d: Read back from address 0x001
        do_read(32'h001);
        if (readData === 32'h12345678) begin
            $display("T1d: PASS - readData = 0x%08X (expected 0x12345678)", readData);
            pass_count = pass_count + 1;
        end else begin
            $display("T1d: FAIL - readData = 0x%08X (expected 0x12345678)", readData);
            fail_count = fail_count + 1;
        end

        // Test 1e: Write to address 0x001 doesn't corrupt address 0x00A
        do_read(32'h00A);
        if (readData === 32'hDEADBEEF) begin
            $display("T1e: PASS - addr 0x00A still holds 0xDEADBEEF after write to 0x001");
            pass_count = pass_count + 1;
        end else begin
            $display("T1e: FAIL - addr 0x00A corrupted, readData = 0x%08X", readData);
            fail_count = fail_count + 1;
        end

        // Test 1f: Write to last valid memory location (address 511 = 0x1FF)
        do_write(32'h1FF, 32'hCAFEBABE);
        do_read(32'h1FF);
        if (readData === 32'hCAFEBABE) begin
            $display("T1f: PASS - last memory location 0x1FF = 0x%08X", readData);
            pass_count = pass_count + 1;
        end else begin
            $display("T1f: FAIL - last memory location 0x1FF = 0x%08X (expected 0xCAFEBABE)", readData);
            fail_count = fail_count + 1;
        end

        // ============================================================
        //  TEST GROUP 2: LED Peripheral (address[9:8] = 01)
        //  Address range 512 - 767  (0x200 - 0x2FF)
        // ============================================================
        $display("\n--- TEST GROUP 2: LED Peripheral Writes ---");

        // Test 2a: Write 0x00FF to LEDs
        do_write(32'h200, 32'h00FF);
        #2;
        if (leds === 16'h00FF) begin
            $display("T2a: PASS - LEDs = 0x%04X (expected 0x00FF)", leds);
            pass_count = pass_count + 1;
        end else begin
            $display("T2a: FAIL - LEDs = 0x%04X (expected 0x00FF)", leds);
            fail_count = fail_count + 1;
        end

        // Test 2b: Write 0xAAAA to LEDs
        do_write(32'h200, 32'hAAAA);
        #2;
        if (leds === 16'hAAAA) begin
            $display("T2b: PASS - LEDs = 0x%04X (expected 0xAAAA)", leds);
            pass_count = pass_count + 1;
        end else begin
            $display("T2b: FAIL - LEDs = 0x%04X (expected 0xAAAA)", leds);
            fail_count = fail_count + 1;
        end

        // Test 2c: Write 0x5555 to LEDs
        do_write(32'h200, 32'h5555);
        #2;
        if (leds === 16'h5555) begin
            $display("T2c: PASS - LEDs = 0x%04X (expected 0x5555)", leds);
            pass_count = pass_count + 1;
        end else begin
            $display("T2c: FAIL - LEDs = 0x%04X (expected 0x5555)", leds);
            fail_count = fail_count + 1;
        end

        // Test 2d: LED write does NOT affect Data Memory
        do_read(32'h00A);
        if (readData === 32'hDEADBEEF) begin
            $display("T2d: PASS - Data Memory unaffected by LED write, addr 0x00A = 0x%08X", readData);
            pass_count = pass_count + 1;
        end else begin
            $display("T2d: FAIL - Data Memory corrupted after LED write, addr 0x00A = 0x%08X", readData);
            fail_count = fail_count + 1;
        end

        // ============================================================
        //  TEST GROUP 3: Switch Peripheral (address[9:8] = 10)
        //  Address range 768 - 1023  (0x300 - 0x3FF)
        // ============================================================
        $display("\n--- TEST GROUP 3: Switch Peripheral Reads ---");

        // Test 3a: Read switches set to 0xABCD
        switches = 16'hABCD;
        do_read(32'h300);
        if (readData[15:0] === 16'hABCD) begin
            $display("T3a: PASS - readData[15:0] = 0x%04X (expected 0xABCD)", readData[15:0]);
            pass_count = pass_count + 1;
        end else begin
            $display("T3a: FAIL - readData[15:0] = 0x%04X (expected 0xABCD)", readData[15:0]);
            fail_count = fail_count + 1;
        end

        // Test 3b: Read switches set to 0x1234
        switches = 16'h1234;
        do_read(32'h300);
        if (readData[15:0] === 16'h1234) begin
            $display("T3b: PASS - readData[15:0] = 0x%04X (expected 0x1234)", readData[15:0]);
            pass_count = pass_count + 1;
        end else begin
            $display("T3b: FAIL - readData[15:0] = 0x%04X (expected 0x1234)", readData[15:0]);
            fail_count = fail_count + 1;
        end

        // Test 3c: Switch read does NOT affect LEDs
        #2;
        if (leds === 16'h5555) begin
            $display("T3c: PASS - LEDs unaffected by switch read, leds = 0x%04X", leds);
            pass_count = pass_count + 1;
        end else begin
            $display("T3c: FAIL - LEDs changed after switch read, leds = 0x%04X", leds);
            fail_count = fail_count + 1;
        end

        // ============================================================
        //  TEST GROUP 4: Address Decoder Isolation
        //  Verify only ONE enable fires per access
        // ============================================================
        $display("\n--- TEST GROUP 4: Decoder Isolation ---");

        // Test 4a: Writing to LED address must NOT write Data Memory
        //          Write 0xFFFFFFFF to LED address then read same
        //          offset in Data Memory - should still be 0
        do_write(32'h205, 32'hFFFFFFFF);  // LED address
        do_read(32'h005);                  // same offset in Data Memory
        if (readData !== 32'hFFFFFFFF) begin
            $display("T4a: PASS - LED write did not bleed into Data Memory (addr 0x005 = 0x%08X)", readData);
            pass_count = pass_count + 1;
        end else begin
            $display("T4a: FAIL - LED write bled into Data Memory (addr 0x005 = 0x%08X)", readData);
            fail_count = fail_count + 1;
        end

        // Test 4b: readData should be 0 when no device is selected
        //          (neither readEnable nor writeEnable asserted)
        @(negedge clk);
        address     = 32'h000;
        readEnable  = 0;
        writeEnable = 0;
        @(posedge clk);
        #1;
        if (readData === 32'b0) begin
            $display("T4b: PASS - readData = 0 when no enable asserted");
            pass_count = pass_count + 1;
        end else begin
            $display("T4b: FAIL - readData = 0x%08X when no enable asserted (expected 0)", readData);
            fail_count = fail_count + 1;
        end

        // ============================================================
        //  TEST GROUP 5: Reset Behaviour
        // ============================================================
        $display("\n--- TEST GROUP 5: Reset ---");

        // Write something to LEDs, then reset, check LEDs cleared
        do_write(32'h200, 32'hFFFF);
        #2;
        rst = 1;
        repeat(2) @(posedge clk);
        #1;
        rst = 0;
        @(posedge clk);
        #1;
        if (leds === 16'h0000) begin
            $display("T5a: PASS - LEDs cleared after reset (leds = 0x%04X)", leds);
            pass_count = pass_count + 1;
        end else begin
            $display("T5a: FAIL - LEDs not cleared after reset (leds = 0x%04X)", leds);
            fail_count = fail_count + 1;
        end

        // ============================================================
        //  SUMMARY
        // ============================================================
        $display("\n============================================");
        $display("  RESULTS: %0d PASSED  |  %0d FAILED", pass_count, fail_count);
        $display("============================================\n");

        if (fail_count == 0)
            $display("ALL TESTS PASSED");
        else
            $display("SOME TESTS FAILED - check waveforms");

        $finish;
    end

    // ================================================================
    //  Waveform Dump (for GTKWave or Vivado simulator)
    // ================================================================
    initial begin
        $dumpfile("Memorysystemtb.vcd");
        $dumpvars(0, Memorysystemtb);
    end

    // ================================================================
    //  Timeout watchdog - stops simulation if it hangs
    // ================================================================
    initial begin
        #100000;
        $display("TIMEOUT: simulation did not finish in time");
        $finish;
    end

endmodule

lab08 final/lab08/project_1/project_1/project_1.sim/sim_1/behav/xsim/Memorysystemtb.vcd
$date
   Mon Mar 16 16:18:47 2026
$end
$version
  2020.1
$end
$timescale
  1ps
$end
$scope module Memorysystemtb $end
$var reg 1 ! clk $end
$var reg 1 " rst $end
$var reg 32 # address [31:0] $end
$var reg 1 $ readEnable $end
$var reg 1 % writeEnable $end
$var reg 32 & writeData [31:0] $end
$var reg 16 ' switches [15:0] $end
$var wire 32 ( readData [31:0] $end
$var wire 16 ) leds [15:0] $end
$var integer 32 * pass_count $end
$var integer 32 + fail_count $end
$scope module dut $end
$var wire 1 , clk $end
$var wire 1 - rst $end
$var wire 32 . address [31:0] $end
$var wire 1 / readEnable $end
$var wire 1 0 writeEnable $end
$var wire 32 1 writeData [31:0] $end
$var wire 16 2 switches [15:0] $end
$var wire 32 ( readData [31:0] $end
$var wire 16 ) leds [15:0] $end
$var wire 1 3 DataMemWrite $end
$var wire 1 4 DataMemRead $end
$var wire 1 5 LEDWrite $end
$var wire 1 6 SwitchRead $end
$var wire 32 7 memReadData [31:0] $end
$scope module decoder $end
$var wire 10 8 address [9:0] $end
$var wire 1 / readEnable $end
$var wire 1 0 writeEnable $end
$var wire 1 3 DataMemWrite $end
$var wire 1 4 DataMemRead $end
$var wire 1 5 LEDWrite $end
$var wire 1 6 SwitchRead $end
$var wire 1 9 isDataMem $end
$var wire 1 : isLED $end
$var wire 1 ; isSwitch $end
$upscope $end
$scope module dmem $end
$var wire 1 , clk $end
$var wire 1 3 MemWrite $end
$var wire 1 4 MemRead $end
$var wire 8 < address [7:0] $end
$var wire 32 1 write_data [31:0] $end
$var wire 32 7 read_data [31:0] $end
$var integer 32 = i $end
$upscope $end
$scope module leds_inst $end
$var wire 1 , clk $end
$var wire 1 - rst $end
$var wire 1 5 LEDWrite $end
$var wire 16 > writeData [15:0] $end
$var wire 16 ) leds [15:0] $end
$var reg 16 ? led_reg [15:0] $end
$upscope $end
$upscope $end
$scope task do_write $end
$var reg 32 @ addr [31:0] $end
$var reg 32 A data [31:0] $end
$upscope $end
$scope task do_read $end
$var reg 32 B addr [31:0] $end
$upscope $end
$upscope $end
$enddefinitions $end
#0
$dumpvars
0!
1"
b0 #
0$
0%
b0 &
b0 '
b0 (
b0 )
b0 *
b0 +
0,
1-
b0 .
0/
00
b0 1
b0 2
03
04
05
06
b0 7
b0 8
19
0:
0;
b0 <
bx =
b0 >
b0 ?
bx @
bx A
bx B
$end
#5000
1!
1,
#10000
0!
0,
#15000
1!
1,
#20000
0!
0,
#25000
1!
1,
#26000
0"
0-
#30000
0!
0,
#35000
1!
1,
b1010 @
b11011110101011011011111011101111 A
#40000
0!
b1010 #
1%
b11011110101011011011111011101111 &
0,
b1010 .
10
b11011110101011011011111011101111 1
13
b0 7
b1010 8
b1010 <
b1011111011101111 >
#45000
1!
1,
b0 7
b100 =
#46000
0%
00
03
b1010 B
#50000
0!
b1010 #
1$
b11101111 (
0,
1/
14
06
b11101111 7
#55000
1!
1,
#56000
0$
b0 (
b1 +
0/
04
06
b0 7
b1 @
b10010001101000101011001111000 A
#60000
0!
b1 #
1%
b10010001101000101011001111000 &
0,
b1 .
10
b10010001101000101011001111000 1
13
b0 7
b1 8
b1 <
b101011001111000 >
#65000
1!
1,
b0 7
b100 =
#66000
0%
00
03
b1 B
#70000
0!
b1 #
1$
b1111000 (
0,
1/
14
06
b1111000 7
#75000
1!
1,
#76000
0$
b0 (
b10 +
0/
04
06
b0 7
b1010 B
#80000
0!
b1010 #
1$
b11101111 (
0,
b1010 .
1/
14
06
b11101111 7
b1010 8
b1010 <
#85000
1!
1,
#86000
0$
b0 (
b11 +
0/
04
06
b0 7
b111111111 @
b11001010111111101011101010111110 A
#90000
0!
b111111111 #
1%
b11001010111111101011101010111110 &
0,
b111111111 .
10
b11001010111111101011101010111110 1
03
04
b0 7
b111111111 8
09
0:
0;
b11111111 <
b1011101010111110 >
#95000
1!
1,
#96000
0%
00
b111111111 B
#100000
0!
b111111111 #
1$
0,
1/
04
06
#105000
1!
1,
#106000
0$
b100 +
0/
04
06
b1000000000 @
b11111111 A
#110000
0!
b1000000000 #
1%
b11111111 &
0,
b1000000000 .
10
b11111111 1
15
b0 7
b1000000000 8
09
1:
0;
b0 <
b11111111 >
#115000
1!
b11111111 )
1,
b11111111 ?
#116000
0%
00
05
#118000
b1 *
b1010101010101010 A
#120000
0!
b1000000000 #
1%
b1010101010101010 &
0,
10
b1010101010101010 1
15
b1010101010101010 >
#125000
1!
b1010101010101010 )
1,
b1010101010101010 ?
#126000
0%
00
05
#128000
b10 *
b101010101010101 A
#130000
0!
b1000000000 #
1%
b101010101010101 &
0,
10
b101010101010101 1
15
b101010101010101 >
#135000
1!
b101010101010101 )
1,
b101010101010101 ?
#136000
0%
00
05
#138000
b11 *
b1010 B
#140000
0!
b1010 #
1$
b11101111 (
0,
b1010 .
1/
14
06
b11101111 7
b1010 8
19
0:
0;
b1010 <
#145000
1!
1,
#146000
0$
b1010101111001101 '
b0 (
b101 +
0/
b1010101111001101 2
04
06
b0 7
b1100000000 B
#150000
0!
b1100000000 #
1$
b1010101111001101 (
0,
b1100000000 .
1/
04
16
b0 7
b1100000000 8
09
0:
1;
b0 <
#155000
1!
1,
#156000
0$
b1001000110100 '
b0 (
b100 *
0/
b1001000110100 2
04
06
#160000
0!
b1100000000 #
1$
b1001000110100 (
0,
1/
04
16
#165000
1!
1,
#166000
0$
b0 (
b101 *
0/
04
06
#168000
b110 *
b1000000101 @
b11111111111111111111111111111111 A
#170000
0!
b1000000101 #
1%
b11111111111111111111111111111111 &
0,
b1000000101 .
10
b11111111111111111111111111111111 1
15
06
b0 7
b1000000101 8
09
1:
0;
b101 <
b1111111111111111 >
#175000
1!
b1111111111111111 )
1,
b1111111111111111 ?
#176000
0%
00
05
b101 B
#180000
0!
b101 #
1$
bx (
0,
b101 .
1/
14
06
bx 7
b101 8
19
0:
0;
b101 <
#185000
1!
1,
#186000
0$
b0 (
b111 *
0/
04
06
b0 7
#190000
0!
b0 #
0,
b0 .
b0 7
b0 8
b0 <
#195000
1!
1,
#196000
b1000 *
b1000000000 @
b1111111111111111 A
#200000
0!
b1000000000 #
1%
b1111111111111111 &
0,
b1000000000 .
10
b1111111111111111 1
03
04
15
b1000000000 8
09
1:
0;
b0 <
b1111111111111111 >
#205000
1!
1,
#206000
0%
00
05
#208000
1"
b0 )
1-
b0 ?
#210000
0!
0,
#215000
1!
1,
#220000
0!
0,
#225000
1!
1,
#226000
0"
0-
