projectlaba/projectlaba.srcs/sources_1/new/mux2.v
`timescale 1ns / 1ps

//2-to-1 multiplexer, 32 bits wide.

//uses 
//PC select mux:
//     sel = PCSrc = (Branch AND Zero)
//     in0 = PC + 4       (sequential, branch not taken)
//     in1 = BranchTarget (branch taken)
//     out = PC_Next

//ALU operand B mux:
//     sel = ALUSrc
//     in0 = ReadData2 from register file (R-type)
//     in1 = imm_out from immGen          (I/S/B-type)
//     out = ALU input B

//Writeback data mux:
//     sel = MemtoReg
//     in0 = ALUResult   (R-type, I-arithmetic)
//     in1 = read_data   (Load instructions)
//     out = WriteData to register file

module mux2 (
    input  wire sel, // select signal
    input  wire [31:0] in0,  // input when sel = 0
    input  wire [31:0] in1, // input when sel = 1
    output reg  [31:0] out  // selected output
);

    always @(*) begin
        if (sel == 1'b0) begin
            out = in0;
        end
        else begin
            out = in1;
        end
    end

endmodule

projectlaba/projectlaba.srcs/sources_1/new/branchAdder.v
//`timescale 1ns / 1ps
//// ============================================================
//// branchAdder.v
//// Lab 11 - Task 1
////
//// Computes the branch target address: PC + (imm << 1)
////
//// Why << 1?
////   RISC-V branch immediates from immGen already have bit[0]=0
////   (branches are halfword aligned). The shift by 1 converts
////   the halfword-count offset into a byte address offset.
////   This gives the correct target byte address.
////
//// Pure combinational - no clock.
//// ============================================================
//module branchAdder (
//    input  wire [31:0] PC,          // current PC
//    input  wire [31:0] imm,         // sign-extended immediate from immGen
//    output wire [31:0] BranchTarget // PC + (imm << 1)
//);

//    assign BranchTarget = PC + (imm << 1);

//endmodule






`timescale 1ns / 1ps

// computes the branch target address: PC + (imm << 1)

module branchAdder (
    input  wire [31:0] PC,  
    input  wire [31:0] imm, 
    output wire [31:0] BranchTarget 
);
    assign BranchTarget = PC + imm; // Removed the redundant << 1
endmodule

projectlaba/projectlaba.srcs/sources_1/new/immGen.v
`timescale 1ns / 1ps

// Immediate Generator
// Extracts and sign-extends the immediate value from a 32-bit RISC-V instruction.
// Supports I-type, S-type, B-type, U-type (LUI/AUIPC), J-type (JAL).

module immGen (
    input  wire [31:0] instruction,
    output reg  [31:0] imm_out
);

    wire [6:0] opcode = instruction[6:0];

    localparam LOAD    = 7'b0000011; // I-type: lw, lh, lb
    localparam I_ARITH = 7'b0010011; // I-type: addi, ori, xori, andi, slli, srli
    localparam JALR    = 7'b1100111; // I-type: jalr
    localparam STORE   = 7'b0100011; // S-type: sw, sh, sb
    localparam BRANCH  = 7'b1100011; // B-type: beq, bne, blt, bge
    localparam LUI     = 7'b0110111; // U-type: lui
    localparam AUIPC   = 7'b0010111; // U-type: auipc
    localparam JAL     = 7'b1101111; // J-type: jal

    always @(*) begin
        case (opcode)

            // --------------------------------------------------
            // I-type: Load, ADDI/ANDI/ORI/XORI/SLLI/SRLI, JALR
            // imm[11:0] = instr[31:20], sign-extended from bit 31
            // --------------------------------------------------
            LOAD, I_ARITH, JALR: begin
                imm_out = {{20{instruction[31]}}, instruction[31:20]};
            end

            // --------------------------------------------------
            // S-type: Store (sw, sh, sb)
            // imm[11:5] = instr[31:25], imm[4:0] = instr[11:7]
            // --------------------------------------------------
            STORE: begin
                imm_out = {{20{instruction[31]}},
                           instruction[31:25],
                           instruction[11:7]};
            end

            // --------------------------------------------------
            // B-type: Branch (beq, bne, blt, bge)
            // Bits are scattered in the encoding; reassemble:
            //   imm[12]   = instr[31]
            //   imm[11]   = instr[7]
            //   imm[10:5] = instr[30:25]
            //   imm[4:1]  = instr[11:8]
            //   imm[0]    = 0  (branches are always halfword-aligned)
            // FIX: previous version was missing the 1'b0 at bit[0],
            // causing every branch target to be 2 bytes short.
            // --------------------------------------------------
            BRANCH: begin
                imm_out = {{19{instruction[31]}},
                           instruction[31],
                           instruction[7],
                           instruction[30:25],
                           instruction[11:8],
                           1'b0};
            end

            // --------------------------------------------------
            // U-type: LUI, AUIPC
            // imm[31:12] = instr[31:12], lower 12 bits are 0
            // --------------------------------------------------
            LUI, AUIPC: begin
                imm_out = {instruction[31:12], 12'b0};
            end

            // --------------------------------------------------
            // J-type: JAL
            //   imm[20]    = instr[31]
            //   imm[10:1]  = instr[30:21]
            //   imm[11]    = instr[20]
            //   imm[19:12] = instr[19:12]
            //   imm[0]     = 0
            // --------------------------------------------------
            JAL: begin
                imm_out = {{11{instruction[31]}},
                           instruction[31],
                           instruction[19:12],
                           instruction[20],
                           instruction[30:21],
                           1'b0};
            end

            default: begin
                imm_out = 32'd0;
            end

        endcase
    end

endmodule

projectlaba/projectlaba.srcs/sources_1/new/pcAdder.v
`timescale 1ns / 1ps



// computes PC + 4.
module pcAdder (
    input  wire [31:0] PC,          //current PC value
    output wire [31:0] PC_Plus4     //PC + 4
);

    assign PC_Plus4 = PC + 32'd4;

endmodule

projectlaba/projectlaba.srcs/sources_1/new/ProgramCounter.v
`timescale 1ns / 1ps

// Program Counter
// Clocked on the fast system clock throughout.
// Only advances when clk_en (the slow_clk pulse from clock_divider) is high,
// so the processor executes one instruction per slow-clock period.
//
// Using a clock enable instead of driving the flip-flop from slow_clk directly
// keeps everything on one clock domain and avoids gated-clock timing issues.

module ProgramCounter (
    input  wire        clk,
    input  wire        clk_en,   // 1-cycle pulse from clock_divider
    input  wire        rst,
    input  wire [31:0] PC_Next,
    output reg  [31:0] PC
);

    always @(posedge clk) begin
        if (rst)
            PC <= 32'h00000000;
        else if (clk_en)
            PC <= PC_Next;
    end

endmodule

projectlaba/projectlaba.srcs/sim_1/new/Task1_tb.v
//`timescale 1ns / 1ps

//// Wires all five Task 1 modules together exactly as they
//// will appear inside TopLevelProcessor.v.
////   TEST 1 - Sequential (PCSrc=0):
////     PC should count  0x00 -> 0x04 -> 0x08 -> 0x0C -> 0x10
////     PC_Plus4 is always PC + 4
////
////   TEST 2 - I-type immediates (immGen):
////     instruction = 0x06400093  -> imm_out = 0x00000064  (+100)
////     instruction = 0xFFC00093  -> imm_out = 0xFFFFFFFC  (-4)
////
////   TEST 3 - S-type immediates (immGen):
////     instruction = 0x00112423  -> imm_out = 0x00000008  (+8)
////     instruction = 0xFE112EA3  -> imm_out = 0xFFFFFFFC  (-4)
////
////   TEST 4 - B-type immediates (immGen):
////     instruction = 0x04000063  -> imm_out = 0x00000004  (+4, branch +8 bytes)
////     instruction = 0xFE000CE3  -> imm_out = 0xFFFFFFFC  (-4, branch -8 bytes)
////
////   TEST 5 - Branch taken (PCSrc=1):
////     PC should jump by (imm_out << 1) each cycle
////     instead of incrementing by 4
////
////   TEST 6 - Back to sequential (PCSrc=0):
////     PC increments by 4 again normally
////
////   TEST 7 - Reset:
////     PC drops back to 0x00000000
////     then resumes counting from 0
//// ============================================================
//module Task1_tb;

//    // -------------------------------------------------------
//    // Testbench driven signals
//    // -------------------------------------------------------
//    reg         clk;
//    reg         rst;
//    reg         PCSrc;          // manually driven here
//                                // in full processor: Branch AND Zero
//    reg  [31:0] instruction;    // manually driven to test immGen

//    // -------------------------------------------------------
//    // Wires connecting the five modules
//    // -------------------------------------------------------
//    wire [31:0] PC;             // output of ProgramCounter
//    wire [31:0] PC_Plus4;       // output of pcAdder
//    wire [31:0] imm_out;        // output of immGen
//    wire [31:0] BranchTarget;   // output of branchAdder
//    wire [31:0] PC_Next;        // output of mux2 -> feeds back into PC

//    // -------------------------------------------------------
//    // Module instantiations
//    // -------------------------------------------------------

//    // 1. Program Counter
//    //    Holds current PC, updates every rising clock edge
//    ProgramCounter u_pc (
//        .clk     (clk),
//        .rst     (rst),
//        .PC_Next (PC_Next),
//        .PC      (PC)
//    );

//    // 2. PC + 4 adder
//    //    Always computes PC + 4, purely combinational
//    pcAdder u_pcAdder (
//        .PC       (PC),
//        .PC_Plus4 (PC_Plus4)
//    );

//    // 3. Immediate generator
//    //    Extracts and sign-extends immediate from instruction word
//    immGen u_immGen (
//        .instruction (instruction),
//        .imm_out     (imm_out)
//    );

//    // 4. Branch target adder
//    //    Computes PC + (imm << 1)
//    branchAdder u_branchAdder (
//        .PC           (PC),
//        .imm          (imm_out),
//        .BranchTarget (BranchTarget)
//    );

//    // 5. Next-PC mux
//    //    sel=0 -> PC+4 (sequential)
//    //    sel=1 -> BranchTarget (branch taken)
//    mux2 u_mux2 (
//        .sel  (PCSrc),
//        .in0  (PC_Plus4),
//        .in1  (BranchTarget),
//        .out  (PC_Next)
//    );

//    // -------------------------------------------------------
//    // 100 MHz clock
//    // -------------------------------------------------------
//    initial clk = 0;
//    always #5 clk = ~clk;

//    // -------------------------------------------------------
//    // Waveform dump - open this vcd in viewer
//    // -------------------------------------------------------
//    initial begin
//        $dumpfile("Task1_tb.vcd");
//        $dumpvars(0, Task1_tb);
//    end

//    // -------------------------------------------------------
//    // Stimulus - no console output, analyse waveforms only
//    // -------------------------------------------------------
//    initial begin

//        // -- initialise all inputs --
//        rst         = 1'b1;
//        PCSrc       = 1'b0;
//        instruction = 32'h00000000;

//        // hold reset for 3 clock cycles
//        repeat(3) @(posedge clk);
//        rst = 1'b0;

//        // ======================================================
//        // TEST 1: Sequential execution
//        // PCSrc = 0 so mux picks PC+4 every cycle
//        // Watch PC in waveform: 0x00, 0x04, 0x08, 0x0C, 0x10
//        // ======================================================
//        PCSrc = 1'b0;
//        repeat(5) @(posedge clk);

//        // ======================================================
//        // TEST 2: immGen - I-type positive immediate
//        // ADDI x1, x0, +100
//        // instruction = 0x06400093
//        // imm_out should show 0x00000064 (100 decimal)
//        // ======================================================
//        instruction = 32'h06400093;
//        repeat(2) @(posedge clk);

//        // ======================================================
//        // TEST 2b: immGen - I-type negative immediate
//        // ADDI x1, x0, -4
//        // instruction = 0xFFC00093
//        // imm_out should show 0xFFFFFFFC
//        // ======================================================
//        instruction = 32'hFFC00093;
//        repeat(2) @(posedge clk);

//        // ======================================================
//        // TEST 3: immGen - S-type positive immediate
//        // SW x1, +8(x2)
//        // instruction = 0x00112423
//        // imm_out should show 0x00000008
//        // ======================================================
//        instruction = 32'h00112423;
//        repeat(2) @(posedge clk);

//        // ======================================================
//        // TEST 3b: immGen - S-type negative immediate
//        // SW x1, -4(x2)
//        // instruction = 0xFE112EA3
//        // imm_out should show 0xFFFFFFFC
//        // ======================================================
//        instruction = 32'hFE112EA3;
//        repeat(2) @(posedge clk);

//        // ======================================================
//        // TEST 4: immGen - B-type positive branch offset
//        // BEQ x0, x0, +8 bytes forward
//        // instruction = 0x04000063
//        // imm_out = 0x00000004
//        // BranchTarget = PC + (4 << 1) = PC + 8
//        // ======================================================
//        instruction = 32'h04000063;
//        repeat(2) @(posedge clk);

//        // ======================================================
//        // TEST 4b: immGen - B-type negative branch offset
//        // BEQ backward -8 bytes
//        // instruction = 0xFE000CE3
//        // imm_out = 0xFFFFFFFC (-4)
//        // BranchTarget = PC + (-4 << 1) = PC - 8
//        // ======================================================
//        instruction = 32'hFE000CE3;
//        repeat(2) @(posedge clk);

//        // ======================================================
//        // TEST 5: Branch taken
//        // Keep the B-type instruction loaded
//        // Set PCSrc = 1 so mux picks BranchTarget
//        // Watch PC jump by -8 each cycle instead of +4
//        // ======================================================
//        PCSrc = 1'b1;
//        repeat(4) @(posedge clk);

//        // ======================================================
//        // TEST 6: Back to sequential
//        // PCSrc = 0 again
//        // PC should resume incrementing by 4
//        // ======================================================
//        PCSrc       = 1'b0;
//        instruction = 32'h00000000;
//        repeat(4) @(posedge clk);

//        // ======================================================
//        // TEST 7: Reset during operation
//        // Assert rst - PC should immediately go to 0x00000000
//        // on the next rising edge
//        // After releasing rst, PC counts from 0 again
//        // ======================================================
//        rst = 1'b1;
//        repeat(3) @(posedge clk);
//        rst = 1'b0;

//        // confirm normal counting resumes from 0
//        PCSrc = 1'b0;
//        repeat(5) @(posedge clk);

//        $finish;
//    end

//endmodule





`timescale 1ns / 1ps

module Task1_tb;

    reg         clk;
    reg         rst;
    reg         PCSrc;          
    reg  [31:0] instruction;   

    // wires connecting the five modules
    wire [31:0] PC; // output of ProgramCounter
    wire [31:0] PC_Plus4; // output of pcAdder
    wire [31:0] imm_out; // output of immGen
    wire [31:0] BranchTarget;// output of branchAdder
    wire [31:0] PC_Next; // output of mux2 -> feeds back into PC

   

    // 1. Program Counter
    ProgramCounter u_pc (
        .clk     (clk),
        .rst     (rst),
        .PC_Next (PC_Next),
        .PC      (PC)
    );

    // 2. PC + 4 adder
    pcAdder u_pcAdder (
        .PC       (PC),
        .PC_Plus4 (PC_Plus4)
    );

    // 3. Immediate generator
    immGen u_immGen (
        .instruction (instruction),
        .imm_out     (imm_out)
    );

    // 4. Branch target adder
   
    branchAdder u_branchAdder (
        .PC           (PC),
        .imm          (imm_out),
        .BranchTarget (BranchTarget)
    );

    // 5. Next-PC mux
    mux2 u_mux2 (
        .sel  (PCSrc),
        .in0  (PC_Plus4),
        .in1  (BranchTarget),
        .out  (PC_Next)
    );

    
    // 100 MHz clock
    
    initial clk = 0;
    always #5 clk = ~clk;

    
    initial begin
        $dumpfile("Task1_tb.vcd");
        $dumpvars(0, Task1_tb);
    end

  
    initial begin

        rst         = 1'b1;
        PCSrc       = 1'b0;
        instruction = 32'h00000000;

        repeat(3) @(posedge clk);
        rst = 1'b0;

        
        // TEST 1: Sequential execution
        // PCSrc=0 so mux picks PC+4 every cycle
        PCSrc = 1'b0;
        repeat(5) @(posedge clk);

        
        // TEST 2a: immGen - I-type positive immediate
        // ADDI x1, x0, +100
        // instruction = 0x06400093
        // imm_out  show 0x00000064
        instruction = 32'h06400093;
        repeat(2) @(posedge clk);

       
        // TEST 2b: immGen - I-type negative immediate
        // ADDI x1, x0, -4
        // instruction = 0xFFC00093
        // imm_out show 0xFFFFFFFC
        instruction = 32'hFFC00093;
        repeat(2) @(posedge clk);


        // TEST 3a: immGen - S-type positive immediate
        // SW x1, +8(x2)
        // instruction = 0x00112423
        // imm_out show 0x00000008
        instruction = 32'h00112423;
        repeat(2) @(posedge clk);

    
        // TEST 3b: immGen - S-type negative immediate
        // SW x1, -4(x2)
        // instruction = 0xFE112EA3
        // imm_out should show 0xFFFFFFFC
        instruction = 32'hFE112EA3;
        repeat(2) @(posedge clk);

      
        // TEST 4a: immGen - B-type positive branch
        // BEQ x0, x0, forward +8 bytes
        // instruction = 0x04000063
        // immGen outputs halfword count: imm_out = 0x00000004
        // BranchTarget = PC + (4 << 1) = PC + 8  correct
        instruction = 32'h04000063;
        repeat(2) @(posedge clk);

       
        // TEST 4b: immGen - B-type negative branch
        // instruction = 0xFE000CE3
        // immGen outputs halfword count: imm_out = 0xFFFFFFFC (-4)
        // BranchTarget = PC + (-4 << 1) = PC - 8  correct
      
        instruction = 32'hFE000CE3;
        repeat(2) @(posedge clk);

        // TEST 5: Branch taken (PCSrc=1)
        // Load BEQ +8 instruction (imm_out = 4)
        // branchAdder: PC + (4 << 1) = PC + 8 each cycle
        // PC jump forward by 8 bytes per cycle
 
        instruction = 32'h04000063;
        PCSrc = 1'b1;
        repeat(4) @(posedge clk);

        
        // TEST 6: PCSrc=0
       
        PCSrc       = 1'b0;
        instruction = 32'h00000000;
        repeat(4) @(posedge clk);

        
        // TEST 7: Reset during operation
       
        rst = 1'b1;
        repeat(3) @(posedge clk);
        rst = 1'b0;

        PCSrc = 1'b0;
        repeat(5) @(posedge clk);

        $finish;
    end

endmodule

projectlaba/projectlaba.sim/sim_1/behav/xsim/Task1_tb.vcd
$date
   Mon Apr 27 14:21:49 2026
$end
$version
  2020.1
$end
$timescale
  1ps
$end
$scope module Task1_tb $end
$var reg 1 ! clk $end
$var reg 1 " rst $end
$var reg 1 # PCSrc $end
$var reg 32 $ instruction [31:0] $end
$var wire 32 % PC [31:0] $end
$var wire 32 & PC_Plus4 [31:0] $end
$var wire 32 ' imm_out [31:0] $end
$var wire 32 ( BranchTarget [31:0] $end
$var wire 32 ) PC_Next [31:0] $end
$scope module u_pc $end
$var wire 1 * clk $end
$var wire 1 + clk_en $end
$var wire 1 , rst $end
$var wire 32 ) PC_Next [31:0] $end
$var reg 32 - PC [31:0] $end
$upscope $end
$scope module u_pcAdder $end
$var wire 32 % PC [31:0] $end
$var wire 32 & PC_Plus4 [31:0] $end
$upscope $end
$scope module u_immGen $end
$var wire 32 . instruction [31:0] $end
$var reg 32 / imm_out [31:0] $end
$var wire 7 0 opcode [6:0] $end
$var parameter 7 1 LOAD [6:0] $end
$var parameter 7 2 I_ARITH [6:0] $end
$var parameter 7 3 JALR [6:0] $end
$var parameter 7 4 STORE [6:0] $end
$var parameter 7 5 BRANCH [6:0] $end
$var parameter 7 6 LUI [6:0] $end
$var parameter 7 7 AUIPC [6:0] $end
$var parameter 7 8 JAL [6:0] $end
$upscope $end
$scope module u_branchAdder $end
$var wire 32 % PC [31:0] $end
$var wire 32 ' imm [31:0] $end
$var wire 32 ( BranchTarget [31:0] $end
$upscope $end
$scope module u_mux2 $end
$var wire 1 9 sel $end
$var wire 32 & in0 [31:0] $end
$var wire 32 ( in1 [31:0] $end
$var reg 32 : out [31:0] $end
$upscope $end
$upscope $end
$enddefinitions $end
#0
$dumpvars
0!
1"
0#
b0 $
bx %
bx &
b0 '
bx (
bx )
0*
z+
1,
bx -
b0 .
b0 /
b0 0
b11 1
b10011 2
b1100111 3
b100011 4
b1100011 5
b110111 6
b10111 7
b1101111 8
09
bx :
$end
#5000
1!
b0 %
b100 &
b0 (
b100 )
1*
b0 -
b100 :
#10000
0!
0*
#15000
1!
1*
#20000
0!
0*
#25000
1!
0"
1*
0,
#30000
0!
0*
#35000
1!
1*
#40000
0!
0*
#45000
1!
1*
#50000
0!
0*
#55000
1!
1*
#60000
0!
0*
#65000
1!
1*
#70000
0!
0*
#75000
1!
b110010000000000000010010011 $
b1100100 '
b1100100 (
1*
b110010000000000000010010011 .
b1100100 /
b10011 0
b100 :
#80000
0!
0*
#85000
1!
1*
#90000
0!
0*
#95000
1!
b11111111110000000000000010010011 $
b11111111111111111111111111111100 '
b11111111111111111111111111111100 (
1*
b11111111110000000000000010010011 .
b11111111111111111111111111111100 /
b100 :
#100000
0!
0*
#105000
1!
1*
#110000
0!
0*
#115000
1!
b100010010010000100011 $
b1000 '
b1000 (
1*
b100010010010000100011 .
b1000 /
b100011 0
b100 :
#120000
0!
0*
#125000
1!
1*
#130000
0!
0*
#135000
1!
b11111110000100010010111010100011 $
b11111111111111111111111111111101 '
b11111111111111111111111111111101 (
1*
b11111110000100010010111010100011 .
b11111111111111111111111111111101 /
b100 :
#140000
0!
0*
#145000
1!
1*
#150000
0!
0*
#155000
1!
b100000000000000000001100011 $
b1000000 '
b1000000 (
1*
b100000000000000000001100011 .
b1000000 /
b1100011 0
b100 :
#160000
0!
0*
#165000
1!
1*
#170000
0!
0*
#175000
1!
b11111110000000000000110011100011 $
b11111111111111111111111111111000 '
b11111111111111111111111111111000 (
1*
b11111110000000000000110011100011 .
b11111111111111111111111111111000 /
b100 :
#180000
0!
0*
#185000
1!
1*
#190000
0!
0*
#195000
1!
1#
b100000000000000000001100011 $
b1000000 '
b1000000 (
b1000000 )
1*
b100000000000000000001100011 .
b1000000 /
19
b1000000 :
#200000
0!
0*
#205000
1!
1*
#210000
0!
0*
#215000
1!
1*
#220000
0!
0*
#225000
1!
1*
#230000
0!
0*
#235000
1!
0#
b0 $
b0 '
b0 (
b100 )
1*
b0 .
b0 /
b0 0
09
b100 :
#240000
0!
0*
#245000
1!
1*
#250000
0!
0*
#255000
1!
1*
#260000
0!
0*
#265000
1!
1*
#270000
0!
0*
#275000
1!
1"
1*
1,
#280000
0!
0*
#285000
1!
1*
#290000
0!
0*
#295000
1!
1*
#300000
0!
0*
#305000
1!
0"
1*
0,
